{
  "main": {
    "id": "a20664dc35427cef",
    "type": "split",
    "children": [
      {
        "id": "64de60fc0b8e2d67",
        "type": "tabs",
        "children": [
          {
            "id": "b179285dd5e2667d",
            "type": "leaf",
            "state": {
              "type": "empty",
              "state": {},
              "icon": "lucide-file",
              "title": "New tab"
            }
          }
        ]
      }
    ],
    "direction": "vertical"
  },
  "left": {
    "id": "984e890ddda24a30",
    "type": "split",
    "children": [
      {
        "id": "f66424ae081c8ec1",
        "type": "tabs",
        "children": [
          {
            "id": "37f0ea15dbea55b2",
            "type": "leaf",
            "state": {
              "type": "file-explorer",
              "state": {
                "sortOrder": "alphabetical",
                "autoReveal": false
              },
              "icon": "lucide-folder-closed",
              "title": "Files"
            }
          },
          {
            "id": "8f0c26ef32f6c575",
            "type": "leaf",
            "state": {
              "type": "search",
              "state": {
                "query": "",
                "matchingCase": false,
                "explainSearch": false,
                "collapseAll": false,
                "extraContext": false,
                "sortOrder": "alphabetical"
              },
              "icon": "lucide-search",
              "title": "Search"
            }
          },
          {
            "id": "8134bb5d0dcf4fd9",
            "type": "leaf",
            "state": {
              "type": "bookmarks",
              "state": {},
              "icon": "lucide-bookmark",
              "title": "Bookmarks"
            }
          }
        ]
      }
    ],
    "direction": "horizontal",
    "width": 465.5
  },
  "right": {
    "id": "3ad3b54b94dd3ed9",
    "type": "split",
    "children": [
      {
        "id": "60ef2942eb3b3cfc",
        "type": "tabs",
        "children": [
          {
            "id": "fd316f39bb5dd3a0",
            "type": "leaf",
            "state": {
              "type": "backlink",
              "state": {
                "file": "Mondo/NPC/Le Corde Dorate_Maleducate/Elowen -Cacciastelle- Kaela.md",
                "collapseAll": true,
                "extraContext": false,
                "sortOrder": "alphabetical",
                "showSearch": false,
                "searchQuery": "",
                "backlinkCollapsed": false,
                "unlinkedCollapsed": true
              },
              "icon": "links-coming-in",
              "title": "Backlinks for Elowen -Cacciastelle- Kaela"
            }
          },
          {
            "id": "43d0f5a7d902b02a",
            "type": "leaf",
            "state": {
              "type": "outgoing-link",
              "state": {
                "file": "Mondo/NPC/Le Corde Dorate_Maleducate/Elowen -Cacciastelle- Kaela.md",
                "linksCollapsed": false,
                "unlinkedCollapsed": true
              },
              "icon": "links-going-out",
              "title": "Outgoing links from Elowen -Cacciastelle- Kaela"
            }
          },
          {
            "id": "5fc9f0418dfa478f",
            "type": "leaf",
            "state": {
              "type": "tag",
              "state": {
                "sortOrder": "frequency",
                "useHierarchy": true,
                "showSearch": false,
                "searchQuery": ""
              },
              "icon": "lucide-tags",
              "title": "Tags"
            }
          },
          {
            "id": "8bd446ce578c2fff",
            "type": "leaf",
            "state": {
              "type": "outline",
              "state": {
                "file": "_Published_/La Storia fin'ora/Riassunto - Parte 5.md",
                "followCursor": false,
                "showSearch": false,
                "searchQuery": ""
              },
              "icon": "lucide-list",
              "title": "Outline of Riassunto - Parte 5"
            }
          },
          {
            "id": "7fcc35d2659be6c7",
            "type": "leaf",
            "state": {
              "type": "DICE_ROLLER_VIEW",
              "state": {},
              "icon": "dices",
              "title": "Dice Tray"
            }
          },
          {
            "id": "8c8e40bc8b035144",
            "type": "leaf",
            "state": {
              "type": "CALENDARIUM",
              "state": {
                "calendar": "ID_bb8bd91a5a69",
                "ephemeral": {
                  "viewing": {
                    "day": 13,
                    "month": 5,
                    "year": 5720
                  },
                  "viewState": 1,
                  "displaying": {
                    "day": 10,
                    "month": 5,
                    "year": 5720
                  },
                  "displayDayNumber": true,
                  "displaySeasonColors": true,
                  "interpolateColors": true,
                  "displayMoons": true,
                  "displayWeather": true
                },
                "id": "ID_daaaba68ab18",
                "child": "ID_0a9bfaea4bf9"
              },
              "icon": "CALENDARIUM",
              "title": "Calendarium"
            }
          }
        ],
        "currentTab": 5
      },
      {
        "id": "95ef7d26878cb06e",
        "type": "tabs",
        "children": [
          {
            "id": "4c4855f06109eb08",
            "type": "leaf",
            "state": {
              "type": "CALENDARIUM_AGENDA",
              "state": {
                "calendar": "ID_bb8bd91a5a69",
                "id": "ID_0a9bfaea4bf9",
                "parent": "ID_daaaba68ab18"
              },
              "icon": "CALENDARIUM_AGENDA",
              "title": "Agenda"
            }
          }
        ]
      }
    ],
    "direction": "horizontal",
    "width": 330.5
  },
  "left-ribbon": {
    "hiddenItems": {
      "switcher:Open quick switcher": false,
      "graph:Open graph view": false,
      "canvas:Create new canvas": false,
      "daily-notes:Open today's daily note": false,
      "templates:Insert template": false,
      "command-palette:Open command palette": false,
      "bases:Create new base": false,
      "obsidian-5e-statblocks:Open Creature pane": false,
      "audio-recorder:Start/stop recording": false,
      "calendarium:Open Calendarium": false
    }
  },
  "active": "8c8e40bc8b035144",
  "lastOpenFiles": [
    "_Published_/La Storia fin'ora/Riassunto - Parte 5.md",
    "Sessioni/Parte 4_2/Parte 4_2.md",
    "_Published_/Mondo/Apparizioni/Scudo magico a forma di mano spezzato (Varkhan)/Descrizione e Visione.md",
    "Sessioni/Parte 4_1/Parte 4_1.md",
    "Mondo/Fazioni/Le Corde Dorate.md",
    "Sessioni/Parte 4_2/Appunti - 4_2.md",
    "Sessioni/Parte 4_1/Appunti - 4_1.md",
    "Mondo/Apparizioni/_Main_.md",
    "_Published_/Mondo/Apparizioni/_Main_.md",
    "Mondo/Geografia/Almas.md",
    "INIZIATIVA e UCCISIONI.md",
    "Mondo/Space Ships/UGP Rebellion.md",
    "Mondo/Fazioni/Egemonia Terran.md",
    "Sessioni/Parte 3_3/Parte 3_3.md",
    "Mondo/Fazioni/Mondi Fantasma.md",
    "Mondo/Fazioni/Liberatori Galattici del Fuoco Celeste.md",
    "Mondo/Ciuschi & co/Regolamento Energia Ciusca.md",
    "_Published_/Mondo/Ciuschi & co/Regolamento Tecnologia Korvosiana.md",
    "_Published_/Mondo/Apparizioni/Carta Apprensura (Fortunata)/Descrizione e Visione.md",
    "Mondo/Ciuschi & co/Regolamento Tecnologia Korvosiana.md",
    "Mondo/Ciuschi & co/Ciuschi Meravigliosi.md",
    "Mondo/Space Ships/Rebellion.pdf",
    "Sessioni/Parte 3_3/Appunti - 3_3.md",
    "_Published_/Mondo/Oggetti Magici/Oggetti Meravigliosi.md",
    "TODO.md",
    "Mondo/NPC/Enemies_npc/Cercatori - giocatori_npc/Comandante Regionale Vossnik.md",
    "Mondo/NPC/Enemies_npc/Cercatori - giocatori_npc/Gruppo 2 - CR 9/Asha Morneve Half-Orc Barbarian 10 - CR 9.md",
    "Shedu.jpeg",
    "_Published_/z_Images/Veldenar.png",
    "_Published_/z_Images/bolla.jpg",
    "Mondo/NPC/Enemies_npc/Cercatori - giocatori_npc/Gruppo 2 - CR 9",
    "Mondo/NPC/Enemies_npc/Cercatori - giocatori_npc/Gruppo 1 - CR 9",
    "Mutant-Captain.jpg",
    "Absalom-Map.png",
    "Mondo/NPC/Enemies_npc/pirati",
    "_Published_/z_Images/varkhan.jpg",
    "_Published_/z_Images/vv.jpeg",
    "_Published_/z_Images/V.jpg",
    "_Published_/z_Images/Varkhan 2.jpg",
    "_Published_/z_Images/varkhan 1.jpg",
    "Mondo/Apparizioni/Sap di Gurnys (Gurnys)",
    "Mondo/Apparizioni/Carta Apprensura (Fortunata)",
    "Mondo/Apparizioni/Mantello Blu Magico (Frankie)"
  ]
}